qonscious/__init__.py
qonscious/run_conditionally.py
qonscious/actions/__init__.py
qonscious/actions/qonscious_action.py
qonscious/actions/qonscious_callable.py
qonscious/actions/qonscious_circuit.py
qonscious/adapters/__init__.py
qonscious/adapters/aer_sampler_adapter.py
qonscious/adapters/aer_simulator_adapter.py
qonscious/adapters/backend_adapter.py
qonscious/adapters/ibm_sampler_adapter.py
qonscious/adapters/ionq_backend_adapter.py
qonscious/checks/__init__.py
qonscious/checks/merit_compliance_check.py
qonscious/foms/__init__.py
qonscious/foms/aggregate_qpu_fom.py
qonscious/foms/figure_of_merit.py
qonscious/foms/packed_chsh.py
qonscious/results/__init__.py
qonscious/results/result_types.py
qonscious/utils/statistics.py
qonscious-0.1.3.dist-info/licenses/LICENSE
qonscious-0.1.3.dist-info/METADATA
qonscious-0.1.3.dist-info/WHEEL
qonscious-0.1.3.dist-info/top_level.txt
qonscious-0.1.3.dist-info/RECORD
