Metadata-Version: 2.4
Name: qonscious
Version: 0.1.3
Summary: Qonscious is a runtime framework designed to support conditional execution of quantum circuits based on resource introspection. It helps you build quantum applications that are aware of backend conditions — such as entanglement, coherence, or fidelity — before execution.
Author-email: Alejandro Fernandez <casco@lifia.info.unlp.edu.ar>, Federico Holik <holik@fisica.unlp.edu.ar>, Marcos Lammers <mlammers@lifia.info.unlp.edu.ar>
License: No license has been chosen for this project yet.
Project-URL: Homepage, https://github.com/lifia-unlp/qonscious
Project-URL: Repository, https://github.com/lifia-unlp/qonscious
Project-URL: Issues, https://github.com/lifia-unlp/qonscious/issues
Project-URL: Documentation, https://lifia-unlp.github.io/qonscious/
Keywords: quantum,qiskit,quantum-computing,runtime,resource-aware,nisq
Classifier: Development Status :: 3 - Alpha
Classifier: Intended Audience :: Science/Research
Classifier: Programming Language :: Python
Classifier: Programming Language :: Python :: 3
Classifier: Programming Language :: Python :: 3.10
Classifier: Programming Language :: Python :: 3.11
Classifier: Programming Language :: Python :: 3.12
Classifier: Topic :: Scientific/Engineering
Requires-Python: >=3.9
License-File: LICENSE
Requires-Dist: qiskit<3,>=2.0
Requires-Dist: qiskit-aer>=0.17
Requires-Dist: qiskit-ibm-runtime>=0.40
Requires-Dist: python-dotenv>=1.0
Requires-Dist: qiskit-ionq
Requires-Dist: typing_extensions>=4.7; python_version < "3.11"
Provides-Extra: dev
Requires-Dist: pytest>=8.4; extra == "dev"
Requires-Dist: ruff>=0.12.12; extra == "dev"
Requires-Dist: pyright; extra == "dev"
Provides-Extra: notebooks
Requires-Dist: ipykernel>=6.29; extra == "notebooks"
Requires-Dist: matplotlib>=3.9; extra == "notebooks"
Requires-Dist: pandas>=2.3; extra == "notebooks"
Provides-Extra: viz
Requires-Dist: graphviz>=0.20; extra == "viz"
Requires-Dist: pydeps>=1.12; extra == "viz"
Provides-Extra: docs
Requires-Dist: mkdocs; extra == "docs"
Requires-Dist: mkdocs-material; extra == "docs"
Requires-Dist: mkdocstrings[python]; extra == "docs"
Requires-Dist: pymdown-extensions; extra == "docs"
Dynamic: license-file
